c10_tools/__init__.py
c10_tools/allbus.py
c10_tools/c10.py
c10_tools/capture.py
c10_tools/common.py
c10_tools/copy.py
c10_tools/dump.py
c10_tools/find.py
c10_tools/from_pcap.py
c10_tools/inspect.py
c10_tools/reindex.py
c10_tools/stat.py
c10_tools/streamcheck.py
c10_tools/timefix.py
c10_tools/wireshark_dissector.lua
c10_tools-1.1.4.dist-info/entry_points.txt
c10_tools-1.1.4.dist-info/WHEEL
c10_tools-1.1.4.dist-info/METADATA
c10_tools-1.1.4.dist-info/license_files/LICENSE.txt
c10_tools-1.1.4.dist-info/RECORD
