Metadata-Version: 2.1
Name: c10-tools
Version: 1.1.4
Summary: Various tools for managing IRIG 106 Chapter 10/11 data
License: BSD3
Author-email: Micah Ferrill <ferrillm@avtest.com>
Requires-Python: >=3.7
Classifier: Development Status :: 4 - Beta
Classifier: Intended Audience :: Developers
Classifier: License :: OSI Approved :: BSD License
Classifier: Operating System :: OS Independent
Classifier: Programming Language :: Python :: 3
Classifier: Programming Language :: Python :: 3 :: Only
Classifier: Programming Language :: Python :: 3.7
Classifier: Programming Language :: Python :: 3.8
Classifier: Programming Language :: Python :: 3.9
Classifier: Topic :: Software Development :: Libraries
Requires-Dist: cbitstruct>=1.0.7
Requires-Dist: docopt>=0.6.2
Requires-Dist: dpkt>=1.9.7
Requires-Dist: matplotlib>=3.3.4
Requires-Dist: pychapter10>=1.1.15
Requires-Dist: s3fs>=0.5.2
Requires-Dist: termcolor>=1.1.0
Requires-Dist: tqdm>=4.48.2
Provides-Extra: ci
Requires-Dist: pytest-azurepipelines==0.8.0; extra == "ci"
Requires-Dist: pytest-cov~=2.10.1; extra == "ci"
Requires-Dist: pytest~=6.2; extra == "ci"
Project-URL: homepage, https://github.com/atac/c10-tools
Project-URL: repository, https://github.com/atac/c10-tools
